pytest_mat_report/__init__.py
pytest_mat_report/plugin.py
pytest_mat_report-0.0.3.dist-info/entry_points.txt
pytest_mat_report-0.0.3.dist-info/WHEEL
pytest_mat_report-0.0.3.dist-info/METADATA
pytest_mat_report-0.0.3.dist-info/RECORD
